redis_canal/__init__.py
redis_canal/agent.py
redis_canal/cli.py
redis_canal/envs.py
redis_canal/exceptions.py
redis_canal/log.py
redis_canal/models.py
redis_canal/producer.py
redis_canal/tools.py
redis_canal/utils.py
redis_canal/adapter/__init__.py
redis_canal/adapter/manager.py
redis_canal/adapter/plugin.py
redis_canal/adapter/impl/__init__.py
redis_canal/adapter/impl/pubsub.py
redis_canal/adapter/impl/sqs.py
redis_canal-0.2.0.dist-info/METADATA
redis_canal-0.2.0.dist-info/WHEEL
redis_canal-0.2.0.dist-info/entry_points.txt
redis_canal-0.2.0.dist-info/licenses/LICENSE
redis_canal-0.2.0.dist-info/RECORD
