Metadata-Version: 2.3
Name: redis_canal
Version: 0.2.0
Summary: redis_canal
Project-URL: Source, https://github.com/wh1isper/redis_canal
Author-email: wh1isper <jizhongsheng957@gmail.com>
License: BSD 3-Clause License
License-File: LICENSE
Keywords: redis_canal
Classifier: Programming Language :: Python :: 3
Classifier: Programming Language :: Python :: 3.10
Classifier: Programming Language :: Python :: 3.11
Classifier: Programming Language :: Python :: 3.12
Requires-Python: >=3.10
Requires-Dist: anyio
Requires-Dist: click
Requires-Dist: loguru
Requires-Dist: pluggy
Requires-Dist: pydantic>=2
Requires-Dist: redis>=4.2.0rc1
Provides-Extra: all
Requires-Dist: boto3; extra == 'all'
Requires-Dist: google-cloud-pubsub; extra == 'all'
Provides-Extra: docs
Requires-Dist: autodoc-pydantic; extra == 'docs'
Requires-Dist: pydata-sphinx-theme; extra == 'docs'
Requires-Dist: sphinx; extra == 'docs'
Requires-Dist: sphinx-click; extra == 'docs'
Provides-Extra: pubsub
Requires-Dist: google-cloud-pubsub; extra == 'pubsub'
Provides-Extra: sqs
Requires-Dist: boto3; extra == 'sqs'
Provides-Extra: test
Requires-Dist: boto3; extra == 'test'
Requires-Dist: boto3-stubs[sqs]; extra == 'test'
Requires-Dist: docker; extra == 'test'
Requires-Dist: google-cloud-pubsub; extra == 'test'
Requires-Dist: pytest; extra == 'test'
Requires-Dist: pytest-asyncio; extra == 'test'
Requires-Dist: pytest-cov; extra == 'test'
